crikit/__init__.py
crikit/_version.py
crikit/fe.py
crikit/fe_adjoint.py
crikit/group.py
crikit/logging.py
crikit/loss.py
crikit/network.py
crikit/network_block.py
crikit/observe_block.py
crikit/observer.py
crikit/overloaded_network.py
crikit/projection.py
crikit/utils.py
crikit/covering/__init__.py
crikit/covering/covering.py
crikit/covering/ufl.py
crikit/cr/__init__.py
crikit/cr/autograd.py
crikit/cr/cr.py
crikit/cr/cr_network.py
crikit/cr/cr_tensorflow.py
crikit/cr/fe.py
crikit/cr/jax_utils.py
crikit/cr/map_builders.py
crikit/cr/numpy.py
crikit/cr/overloaded.py
crikit/cr/quadrature.py
crikit/cr/space_builders.py
crikit/cr/stdnumeric.py
crikit/cr/types.py
crikit/cr/ufl.py
crikit/invariants/__init__.py
crikit/invariants/invariants.py
crikit/invariants/utils.py
pyadjoint_utils/__init__.py
pyadjoint_utils/adjfloat.py
pyadjoint_utils/block.py
pyadjoint_utils/block_variable.py
pyadjoint_utils/callback.py
pyadjoint_utils/control.py
pyadjoint_utils/convert.py
pyadjoint_utils/drivers.py
pyadjoint_utils/identity.py
pyadjoint_utils/minimize.py
pyadjoint_utils/reduced_function.py
pyadjoint_utils/reduced_function_numpy.py
pyadjoint_utils/tape.py
pyadjoint_utils/tape_block.py
pyadjoint_utils/verification.py
pyadjoint_utils/fenics_adjoint/__init__.py
pyadjoint_utils/fenics_adjoint/array.py
pyadjoint_utils/fenics_adjoint/assembly.py
pyadjoint_utils/fenics_adjoint/utils.py
pyadjoint_utils/jax_adjoint/__init__.py
pyadjoint_utils/jax_adjoint/array.py
pyadjoint_utils/jax_adjoint/blocks.py
pyadjoint_utils/jax_adjoint/jax.py
pyadjoint_utils/numpy_adjoint/__init__.py
pyadjoint_utils/numpy_adjoint/array.py
pyadjoint_utils/numpy_adjoint/autograd.py
pyadjoint_utils/onnx_adjoint/__init__.py
pyadjoint_utils/onnx_adjoint/onnx.py
pyadjoint_utils/solving/__init__.py
pyadjoint_utils/solving/equation.py
pyadjoint_utils/solving/equation_solver.py
pyadjoint_utils/solving/snes_solver.py
pyadjoint_utils/tensorflow_adjoint/__init__.py
pyadjoint_utils/tensorflow_adjoint/tensorflow_block.py
crikit-0.1.5.dist-info/LICENSE-APACHE
crikit-0.1.5.dist-info/LICENSE-MIT
crikit-0.1.5.dist-info/LICENSE.md
crikit-0.1.5.dist-info/METADATA
crikit-0.1.5.dist-info/WHEEL
crikit-0.1.5.dist-info/dependency_links.txt
crikit-0.1.5.dist-info/top_level.txt
crikit-0.1.5.dist-info/RECORD
