Metadata-Version: 2.1
Name: crikit
Version: 0.1.5
Summary: Constitutive Relation Inference Toolkit
Home-page: https://gitlab.com/crikit/crikit
Author: CRIKit Team
License: UNKNOWN
Project-URL: Bug Tracker, https://gitlab.com/crikit/crikit/issues
Project-URL: Documentation, https://crikit.science/documentation
Platform: UNKNOWN
Classifier: Programming Language :: Python :: 3
Classifier: Programming Language :: Python :: 3.7
Classifier: License :: OSI Approved :: MIT License
Classifier: Operating System :: OS Independent
Requires-Python: >=3.7
License-File: LICENSE-APACHE
License-File: LICENSE-MIT
License-File: LICENSE.md
Requires-Dist: dolfin-adjoint (>=2019.1.1)
Requires-Dist: numpy
Requires-Dist: autograd
Requires-Dist: petsc4py (>=3.11.0)
Requires-Dist: jax
Requires-Dist: jaxlib
Provides-Extra: all
Requires-Dist: pytest (>=3.10) ; extra == 'all'
Requires-Dist: pytest-rerunfailures ; extra == 'all'
Requires-Dist: flake8 ; extra == 'all'
Requires-Dist: coverage ; extra == 'all'
Requires-Dist: matplotlib ; extra == 'all'
Requires-Dist: flax ; extra == 'all'
Requires-Dist: tensorflow (>=2.0) ; extra == 'all'
Requires-Dist: sphinx ; extra == 'all'
Requires-Dist: myst-nb ; extra == 'all'
Requires-Dist: sphinxcontrib-bibtex ; extra == 'all'
Requires-Dist: sphinxcontrib-katex ; extra == 'all'
Requires-Dist: pydata-sphinx-theme ; extra == 'all'
Requires-Dist: linkify-it-py ; extra == 'all'
Requires-Dist: black ; extra == 'all'
Requires-Dist: pre-commit ; extra == 'all'
Requires-Dist: build ; extra == 'all'
Provides-Extra: dev
Requires-Dist: black ; extra == 'dev'
Requires-Dist: pre-commit ; extra == 'dev'
Requires-Dist: build ; extra == 'dev'
Provides-Extra: doc
Requires-Dist: sphinx ; extra == 'doc'
Requires-Dist: myst-nb ; extra == 'doc'
Requires-Dist: sphinxcontrib-bibtex ; extra == 'doc'
Requires-Dist: sphinxcontrib-katex ; extra == 'doc'
Requires-Dist: pydata-sphinx-theme ; extra == 'doc'
Requires-Dist: linkify-it-py ; extra == 'doc'
Provides-Extra: flax
Requires-Dist: flax ; extra == 'flax'
Provides-Extra: tensorflow
Requires-Dist: tensorflow (>=2.0) ; extra == 'tensorflow'
Provides-Extra: test
Requires-Dist: pytest (>=3.10) ; extra == 'test'
Requires-Dist: pytest-rerunfailures ; extra == 'test'
Requires-Dist: flake8 ; extra == 'test'
Requires-Dist: coverage ; extra == 'test'
Provides-Extra: visualization
Requires-Dist: matplotlib ; extra == 'visualization'
